jps_static_audit_utils/__init__.py
jps_static_audit_utils/constants.py
jps_static_audit_utils/finding.py
jps_static_audit_utils/hardcoded_path_reporter.py
jps_static_audit_utils/logging_helper.py
jps_static_audit_utils/writer.py
jps_static_audit_utils-0.2.0.dist-info/licenses/LICENSE
jps_static_audit_utils-0.2.0.dist-info/METADATA
jps_static_audit_utils-0.2.0.dist-info/WHEEL
jps_static_audit_utils-0.2.0.dist-info/entry_points.txt
jps_static_audit_utils-0.2.0.dist-info/top_level.txt
jps_static_audit_utils-0.2.0.dist-info/RECORD
