Metadata-Version: 2.4
Name: jps-static-audit-utils
Version: 0.2.0
Summary: Collection of Python utils for static code analysis on Perl, Python and R scripts.
Author-email: Jaideep Sundaram <jai.python3@gmail.com>
License: MIT
Project-URL: Homepage, https://github.com/jai-python3/jps-static-audit-utils
Project-URL: Repository, https://github.com/jai-python3/jps-static-audit-utils
Project-URL: Issues, https://github.com/jai-python3/jps-static-audit-utils/issues
Keywords: cookiecutter,bootstrap,project-generator,automation
Classifier: Programming Language :: Python :: 3
Classifier: License :: OSI Approved :: MIT License
Classifier: Operating System :: OS Independent
Requires-Python: >=3.10
License-File: LICENSE
Requires-Dist: typer>=0.12.3
Provides-Extra: test
Requires-Dist: pytest>=8.0.0; extra == "test"
Provides-Extra: dev
Requires-Dist: flake8>=7.0.0; extra == "dev"
Requires-Dist: black>=24.0.0; extra == "dev"
Requires-Dist: build>=1.2.1; extra == "dev"
Requires-Dist: twine>=5.0.0; extra == "dev"
Requires-Dist: pytest>=8.0.0; extra == "dev"
Requires-Dist: pytest-cov>=5.0.0; extra == "dev"
Requires-Dist: isort>=5.13.0; extra == "dev"
Requires-Dist: codecov>=2.1.13; extra == "dev"
Requires-Dist: autoflake>=2.3.1; extra == "dev"
Requires-Dist: pre-commit>=3.8.0; extra == "dev"
Requires-Dist: bandit>=1.7.9; extra == "dev"
Requires-Dist: vulture>=2.11; extra == "dev"
Requires-Dist: flynt>=1.0.1; extra == "dev"
Requires-Dist: pydocstyle>=6.3.0; extra == "dev"
Requires-Dist: darglint>=1.8.1; extra == "dev"
Requires-Dist: mypy>=1.12.1; extra == "dev"
Requires-Dist: bump-my-version>=1.0.1; extra == "dev"
Requires-Dist: git-changelog>=2.7.0; extra == "dev"
Dynamic: license-file
